ask_academic_dates/__init__.py
ask_academic_dates-0.2.4.dist-info/WHEEL
ask_academic_dates-0.2.4.dist-info/METADATA
ask_academic_dates-0.2.4.dist-info/RECORD
