Metadata-Version: 2.1
Name: ask-academic-dates
Version: 0.2.4
Summary: Ask Scholars Portal Academic Date finder
Home-page: https://github.com/guinslym/ask_academic_dates
License: MIT
Keywords: Ask,Scholars Portal,Ontario
Author: Guinsly Mondesir
Author-email: guinslym@gmail.com
Requires-Python: >=3.4,<4.0
Classifier: License :: OSI Approved :: MIT License
Classifier: Operating System :: OS Independent
Classifier: Programming Language :: Python :: 3
Classifier: Programming Language :: Python :: 3.4
Classifier: Programming Language :: Python :: 3.5
Classifier: Programming Language :: Python :: 3.6
Classifier: Programming Language :: Python :: 3.7
Classifier: Topic :: Software Development :: Documentation
Classifier: Topic :: Software Development :: Libraries :: Python Modules
Classifier: Topic :: Software Development :: Quality Assurance
Project-URL: Repository, https://github.com/guinslym/ask_academic_dates
